Workbook

Sheet Read me
A1: IEEE journals — open-access model, APC 2026 and time to first decision
A2: • Hybrid = subscription journal. Publishing is FREE unless you choose open access (then you pay the APC). Overlength page charges may still apply.
A3: • Fully open access = every accepted article pays the APC. There is no free option (waivers exist for low-income countries).
A4: • APCs are formulas that read the 'Pricing rules' sheet — change a blue cell there and every journal updates. A few titles have their own price (set in the data).
A5: • Decision times: IEEE does not publish a time to first decision for most journals. Figures appear only where an IEEE society or a named source gives one; the source type is shown next to it.
A6: • Red notes: open-access model not confirmed in 2026 sources — check the journal's author page.
A7: Generated from data/journals.yml in github.com/aionndc22/ieee-conference-deadlines — contributions welcome. Not affiliated with IEEE.

Sheet Pricing rules
A1: IEEE open-access pricing — 2026 submissions (last checked 2026-10-16)
A2: Blue cells are inputs; the Journals sheet recalculates from them.
A3: Publishing model | B3: APC 2026 (US$) | C3: If you don't choose open access | D3: What it means
A4: Hybrid | B4: 2800 | C4: Free (overlength page charges may apply) | D4: Subscription journal. Publishing is free unless you choose open access; mandatory overlength page charges may apply.
A5: Fully open access | B5: 2160 | C5: Not available — OA only | D5: Gold open access: every accepted article pays the APC. Standard rate for most fully OA titles; a few titles differ.
A6: Hybrid magazine | B6: 2995 | C6: Free (most articles are invited) | D6: Magazine with an optional open-access fee (most magazines).
A8: Discounts
A9: IEEE member discount | B9: 0.05
A10: IEEE Society member discount | B10: 0.2 | C10: Discounts do not stack; students excluded.
A12: Sources
A13: https://open.ieee.org/for-authors/article-processing-charges/
A14: https://journals.ieeeauthorcenter.ieee.org/wp-content/uploads/sites/7/2026-07-30-IEEE-Article-Processing-Charges-List.pdf
A15: https://ieee-aess.org/apc-open-access
A16: https://open.ieee.org/for-authors/ieee-low-and-lower-middle-income-country-open-access-discount-program/

Sheet Summary by track
A1: IEEE journals by track — counts by publishing model
A3: Track | B3: Journals | C3: Hybrid | D3: Fully open access | E3: With a decision-time figure
A4: Aerospace, Radar & Navigation | B4: =COUNTIF(Journals!$A$2:$A$175,A4) | C4: =COUNTIFS(Journals!$A$2:$A$175,A4,Journals!$E$2:$E$175,"Hybrid") | D4: =COUNTIFS(Journals!$A$2:$A$175,A4,Journals!$E$2:$E$175,"Fully open access") | E4: =COUNTIFS(Journals!$A$2:$A$175,A4,Journals!$I$2:$I$175,"<>Not published")
A5: Communications & Networking | B5: =COUNTIF(Journals!$A$2:$A$175,A5) | C5: =COUNTIFS(Journals!$A$2:$A$175,A5,Journals!$E$2:$E$175,"Hybrid") | D5: =COUNTIFS(Journals!$A$2:$A$175,A5,Journals!$E$2:$E$175,"Fully open access") | E5: =COUNTIFS(Journals!$A$2:$A$175,A5,Journals!$I$2:$I$175,"<>Not published")
A6: Signal, Image & Speech Processing | B6: =COUNTIF(Journals!$A$2:$A$175,A6) | C6: =COUNTIFS(Journals!$A$2:$A$175,A6,Journals!$E$2:$E$175,"Hybrid") | D6: =COUNTIFS(Journals!$A$2:$A$175,A6,Journals!$E$2:$E$175,"Fully open access") | E6: =COUNTIFS(Journals!$A$2:$A$175,A6,Journals!$I$2:$I$175,"<>Not published")
A7: AI, Computing & Software | B7: =COUNTIF(Journals!$A$2:$A$175,A7) | C7: =COUNTIFS(Journals!$A$2:$A$175,A7,Journals!$E$2:$E$175,"Hybrid") | D7: =COUNTIFS(Journals!$A$2:$A$175,A7,Journals!$E$2:$E$175,"Fully open access") | E7: =COUNTIFS(Journals!$A$2:$A$175,A7,Journals!$I$2:$I$175,"<>Not published")
A8: Antennas, Microwaves & EM | B8: =COUNTIF(Journals!$A$2:$A$175,A8) | C8: =COUNTIFS(Journals!$A$2:$A$175,A8,Journals!$E$2:$E$175,"Hybrid") | D8: =COUNTIFS(Journals!$A$2:$A$175,A8,Journals!$E$2:$E$175,"Fully open access") | E8: =COUNTIFS(Journals!$A$2:$A$175,A8,Journals!$I$2:$I$175,"<>Not published")
A9: Photonics, Quantum & Plasma | B9: =COUNTIF(Journals!$A$2:$A$175,A9) | C9: =COUNTIFS(Journals!$A$2:$A$175,A9,Journals!$E$2:$E$175,"Hybrid") | D9: =COUNTIFS(Journals!$A$2:$A$175,A9,Journals!$E$2:$E$175,"Fully open access") | E9: =COUNTIFS(Journals!$A$2:$A$175,A9,Journals!$I$2:$I$175,"<>Not published")
A10: Geoscience, Remote Sensing & Ocean | B10: =COUNTIF(Journals!$A$2:$A$175,A10) | C10: =COUNTIFS(Journals!$A$2:$A$175,A10,Journals!$E$2:$E$175,"Hybrid") | D10: =COUNTIFS(Journals!$A$2:$A$175,A10,Journals!$E$2:$E$175,"Fully open access") | E10: =COUNTIFS(Journals!$A$2:$A$175,A10,Journals!$I$2:$I$175,"<>Not published")
A11: Circuits, Devices & Semiconductors | B11: =COUNTIF(Journals!$A$2:$A$175,A11) | C11: =COUNTIFS(Journals!$A$2:$A$175,A11,Journals!$E$2:$E$175,"Hybrid") | D11: =COUNTIFS(Journals!$A$2:$A$175,A11,Journals!$E$2:$E$175,"Fully open access") | E11: =COUNTIFS(Journals!$A$2:$A$175,A11,Journals!$I$2:$I$175,"<>Not published")
A12: Power, Energy & Industrial Electronics | B12: =COUNTIF(Journals!$A$2:$A$175,A12) | C12: =COUNTIFS(Journals!$A$2:$A$175,A12,Journals!$E$2:$E$175,"Hybrid") | D12: =COUNTIFS(Journals!$A$2:$A$175,A12,Journals!$E$2:$E$175,"Fully open access") | E12: =COUNTIFS(Journals!$A$2:$A$175,A12,Journals!$I$2:$I$175,"<>Not published")
A13: Control, Robotics & Systems | B13: =COUNTIF(Journals!$A$2:$A$175,A13) | C13: =COUNTIFS(Journals!$A$2:$A$175,A13,Journals!$E$2:$E$175,"Hybrid") | D13: =COUNTIFS(Journals!$A$2:$A$175,A13,Journals!$E$2:$E$175,"Fully open access") | E13: =COUNTIFS(Journals!$A$2:$A$175,A13,Journals!$I$2:$I$175,"<>Not published")
A14: Vehicles & Transportation | B14: =COUNTIF(Journals!$A$2:$A$175,A14) | C14: =COUNTIFS(Journals!$A$2:$A$175,A14,Journals!$E$2:$E$175,"Hybrid") | D14: =COUNTIFS(Journals!$A$2:$A$175,A14,Journals!$E$2:$E$175,"Fully open access") | E14: =COUNTIFS(Journals!$A$2:$A$175,A14,Journals!$I$2:$I$175,"<>Not published")
A15: Instrumentation, Sensors & Measurement | B15: =COUNTIF(Journals!$A$2:$A$175,A15) | C15: =COUNTIFS(Journals!$A$2:$A$175,A15,Journals!$E$2:$E$175,"Hybrid") | D15: =COUNTIFS(Journals!$A$2:$A$175,A15,Journals!$E$2:$E$175,"Fully open access") | E15: =COUNTIFS(Journals!$A$2:$A$175,A15,Journals!$I$2:$I$175,"<>Not published")
... A17: Multidisciplinary, Education & Society | B17: =COUNTIF(Journals!$A$2:$A$175,A17) | C17: =COUNTIFS(Journals!$A$2:$A$175,A17,Journals!$E$2:$E$175,"Hybrid") | D17: =COUNTIFS(Journals!$A$2:$A$175,A17,Journals!$E$2:$E$175,"Fully open access") | E17: =COUNTIFS(Journals!$A$2:$A$175,A17,Journals!$I$2:$I$175,"<>Not published")
A18: Total | B18: =SUM(B4:B17) | C18: =SUM(C4:C17) | D18: =SUM(D4:D17) | E18: =SUM(E4:E17)

Sheet Journals
A1: Track | B1: Journal | C1: Acronym | D1: Type | E1: OA model | F1: APC 2026 (US$) | G1: APC for society member (US$) | H1: Cost without OA | I1: Avg. time to first decision | J1: Decision-time source | K1: Source link | L1: Society | M1: Notes
A2: Aerospace, Radar & Navigation | B2: IEEE Transactions on Aerospace and Electronic Systems | C2: TAES | D2: Transactions | E2: Hybrid | F2: =INDEX('Pricing rules'!$B$4:$B$6,MATCH(E2,'Pricing rules'!$A$4:$A$6,0)) | G2: =ROUND(F2*(1-'Pricing rules'!$B$10),0) | H2: Free (overlength page charges may apply) | I2: ~22.6 weeks first review round | J2: Crowd-sourced (SciRev) | K2: https://scirev.org/journal/ieee-transactions-on-aerospace-and-electronic-systems/ | L2: AESS | M2: AESS flagship. APC US$2,800 confirmed by AESS for 2026.
A3: Aerospace, Radar & Navigation | B3: IEEE Transactions on Radar Systems | C3: T-RS | D3: Transactions | E3: Hybrid | F3: =INDEX('Pricing rules'!$B$4:$B$6,MATCH(E3,'Pricing rules'!$A$4:$A$6,0)) | G3: =ROUND(F3*(1-'Pricing rules'!$B$10),0) | H3: Free (overlength page charges may apply) | I3: Not published | L3: AESS | M3: Open-access model not confirmed for 2026 — check the journal's author page.
A4: Aerospace, Radar & Navigation | B4: IEEE Journal on Miniaturization for Air and Space Systems | C4: J-MASS | D4: Journal | E4: Hybrid | F4: =INDEX('Pricing rules'!$B$4:$B$6,MATCH(E4,'Pricing rules'!$A$4:$A$6,0)) | G4: =ROUND(F4*(1-'Pricing rules'!$B$10),0) | H4: Free (overlength page charges may apply) | I4: Not published | L4: AESS | M4: Open-access model not confirmed for 2026 — check the journal's author page.
A5: Aerospace, Radar & Navigation | B5: IEEE Journal of Indoor and Seamless Positioning and Navigation | C5: J-ISPIN | D5: Journal | E5: Fully open access | F5: =INDEX('Pricing rules'!$B$4:$B$6,MATCH(E5,'Pricing rules'!$A$4:$A$6,0)) | G5: =ROUND(F5*(1-'Pricing rules'!$B$10),0) | H5: Not available — OA only | I5: Not published | M5: Gold OA (IEEE Sensors Council, SPS, IMS).
A6: Aerospace, Radar & Navigation | B6: IEEE Journal of Radio Frequency Identification | C6: JRFID | D6: Journal | E6: Hybrid | F6: =INDEX('Pricing rules'!$B$4:$B$6,MATCH(E6,'Pricing rules'!$A$4:$A$6,0)) | G6: =ROUND(F6*(1-'Pricing rules'!$B$10),0) | H6: Free (overlength page charges may apply) | I6: Not published | M6: Open-access model not confirmed for 2026 — check the journal's author page.
A7: Communications & Networking | B7: IEEE Journal on Selected Areas in Communications | C7: JSAC | D7: Journal | E7: Hybrid | F7: =INDEX('Pricing rules'!$B$4:$B$6,MATCH(E7,'Pricing rules'!$A$4:$A$6,0)) | G7: =ROUND(F7*(1-'Pricing rules'!$B$10),0) | H7: Free (overlength page charges may apply) | I7: 4–8 months to first decision | J7: Third-party estimate | K7: https://manusights.com/blog/average-review-times-100-journals-2026 | M7: Special-issue driven.
A8: Communications & Networking | B8: IEEE Transactions on Communications | C8: TCOM | D8: Transactions | E8: Hybrid | F8: =INDEX('Pricing rules'!$B$4:$B$6,MATCH(E8,'Pricing rules'!$A$4:$A$6,0)) | G8: =ROUND(F8*(1-'Pricing rules'!$B$10),0) | H8: Free (overlength page charges may apply) | I8: 3–5 months to first decision | J8: Third-party estimate | K8: https://manusights.com/blog/average-review-times-100-journals-2026
A9: Communications & Networking | B9: IEEE Transactions on Wireless Communications | C9: TWC | D9: Transactions | E9: Hybrid | F9: =INDEX('Pricing rules'!$B$4:$B$6,MATCH(E9,'Pricing rules'!$A$4:$A$6,0)) | G9: =ROUND(F9*(1-'Pricing rules'!$B$10),0) | H9: Free (overlength page charges may apply) | I9: 3–5 months to first decision (sources conflict) | J9: Third-party estimate | K9: https://manusights.com/blog/ieee-transactions-on-wireless-communications-submission-guide
A10: Communications & Networking | B10: IEEE Communications Letters | C10: COMML | D10: Letters | E10: Hybrid | F10: =INDEX('Pricing rules'!$B$4:$B$6,MATCH(E10,'Pricing rules'!$A$4:$A$6,0)) | G10: =ROUND(F10*(1-'Pricing rules'!$B$10),0) | H10: Free (overlength page charges may apply) | I10: Not published
A11: Communications & Networking | B11: IEEE Wireless Communications Letters | C11: WCL | D11: Letters | E11: Hybrid | F11: =INDEX('Pricing rules'!$B$4:$B$6,MATCH(E11,'Pricing rules'!$A$4:$A$6,0)) | G11: =ROUND(F11*(1-'Pricing rules'!$B$10),0) | H11: Free (overlength page charges may apply) | I11: Not published
A12: Communications & Networking | B12: IEEE Communications Surveys & Tutorials | C12: COMST | D12: Journal | E12: Hybrid | F12: =INDEX('Pricing rules'!$B$4:$B$6,MATCH(E12,'Pricing rules'!$A$4:$A$6,0)) | G12: =ROUND(F12*(1-'Pricing rules'!$B$10),0) | H12: Free (overlength page charges may apply) | I12: Not published | M12: Surveys/tutorials only.
A13: Communications & Networking | B13: IEEE Transactions on Networking (formerly IEEE/ACM ToN) | C13: ToN | D13: Transactions | E13: Hybrid | F13: =INDEX('Pricing rules'!$B$4:$B$6,MATCH(E13,'Pricing rules'!$A$4:$A$6,0)) | G13: =ROUND(F13*(1-'Pricing rules'!$B$10),0) | H13: Free (overlength page charges may apply) | I13: ~5 months (editor assignment to first decision) | J13: Official (IEEE ComSoc) | K13: https://www.comsoc.org/publications/journals/ieee-tnet/policies-guidelines
A14: Communications & Networking | B14: IEEE Transactions on Network and Service Management | C14: TNSM | D14: Transactions | E14: Hybrid | F14: =INDEX('Pricing rules'!$B$4:$B$6,MATCH(E14,'Pricing rules'!$A$4:$A$6,0)) | G14: =ROUND(F14*(1-'Pricing rules'!$B$10),0) | H14: Free (overlength page charges may apply) | I14: Not published
A15: Communications & Networking | B15: IEEE Transactions on Cognitive Communications and Networking | C15: TCCN | D15: Transactions | E15: Hybrid | F15: =INDEX('Pricing rules'!$B$4:$B$6,MATCH(E15,'Pricing rules'!$A$4:$A$6,0)) | G15: =ROUND(F15*(1-'Pricing rules'!$B$10),0) | H15: Free (overlength page charges may apply) | I15: Not published
A16: Communications & Networking | B16: IEEE Transactions on Green Communications and Networking | C16: TGCN | D16: Transactions | E16: Hybrid | F16: =INDEX('Pricing rules'!$B$4:$B$6,MATCH(E16,'Pricing rules'!$A$4:$A$6,0)) | G16: =ROUND(F16*(1-'Pricing rules'!$B$10),0) | H16: Free (overlength page charges may apply) | I16: Not published
A17: Communications & Networking | B17: IEEE Transactions on Mobile Computing | C17: TMC | D17: Transactions | E17: Hybrid | F17: =INDEX('Pricing rules'!$B$4:$B$6,MATCH(E17,'Pricing rules'!$A$4:$A$6,0)) | G17: =ROUND(F17*(1-'Pricing rules'!$B$10),0) | H17: Free (overlength page charges may apply) | I17: Not published
A18: Communications & Networking | B18: IEEE Internet of Things Journal | C18: IoT-J | D18: Journal | E18: Hybrid | F18: =INDEX('Pricing rules'!$B$4:$B$6,MATCH(E18,'Pricing rules'!$A$4:$A$6,0)) | G18: =ROUND(F18*(1-'Pricing rules'!$B$10),0) | H18: Free (overlength page charges may apply) | I18: ~6.9 weeks to first decision | J18: Third-party estimate | K18: https://manusights.com/blog/ieee-internet-of-things-journal-submission-guide
A19: Communications & Networking | B19: IEEE Transactions on Network Science and Engineering | C19: TNSE | D19: Transactions | E19: Hybrid | F19: =INDEX('Pricing rules'!$B$4:$B$6,MATCH(E19,'Pricing rules'!$A$4:$A$6,0)) | G19: =ROUND(F19*(1-'Pricing rules'!$B$10),0) | H19: Free (overlength page charges may apply) | I19: Not published
A20: Communications & Networking | B20: IEEE Transactions on Molecular, Biological, and Multi-Scale Communications | C20: TMBMC | D20: Transactions | E20: Hybrid | F20: =INDEX('Pricing rules'!$B$4:$B$6,MATCH(E20,'Pricing rules'!$A$4:$A$6,0)) | G20: =ROUND(F20*(1-'Pricing rules'!$B$10),0) | H20: Free (overlength page charges may apply) | I20: Not published
A21: Communications & Networking | B21: IEEE Transactions on Machine Learning in Communications and Networking | C21: TMLCN | D21: Transactions | E21: Fully open access | F21: =INDEX('Pricing rules'!$B$4:$B$6,MATCH(E21,'Pricing rules'!$A$4:$A$6,0)) | G21: =ROUND(F21*(1-'Pricing rules'!$B$10),0) | H21: Not available — OA only | I21: Not published | M21: Open-access model not confirmed for 2026 — check the journal's author page.
A22: Communications & Networking | B22: IEEE Networking Letters | C22: LNET | D22: Letters | E22: Hybrid | F22: =INDEX('Pricing rules'!$B$4:$B$6,MATCH(E22,'Pricing rules'!$A$4:$A$6,0)) | G22: =ROUND(F22*(1-'Pricing rules'!$B$10),0) | H22: Free (overlength page charges may apply) | I22: Not published
A23: Communications & Networking | B23: IEEE Transactions on Broadcasting | C23: TBC | D23: Transactions | E23: Hybrid | F23: =INDEX('Pricing rules'!$B$4:$B$6,MATCH(E23,'Pricing rules'!$A$4:$A$6,0)) | G23: =ROUND(F23*(1-'Pricing rules'!$B$10),0) | H23: Free (overlength page charges may apply) | I23: Not published
A24: Communications & Networking | B24: IEEE Transactions on Information Theory | C24: TIT | D24: Transactions | E24: Hybrid | F24: =INDEX('Pricing rules'!$B$4:$B$6,MATCH(E24,'Pricing rules'!$A$4:$A$6,0)) | G24: =ROUND(F24*(1-'Pricing rules'!$B$10),0) | H24: Free (overlength page charges may apply) | I24: Not published
A25: Communications & Networking | B25: IEEE Journal on Selected Areas in Information Theory | C25: JSAIT | D25: Journal | E25: Hybrid | F25: =INDEX('Pricing rules'!$B$4:$B$6,MATCH(E25,'Pricing rules'!$A$4:$A$6,0)) | G25: =ROUND(F25*(1-'Pricing rules'!$B$10),0) | H25: Free (overlength page charges may apply) | I25: Not published | M25: Open-access model not confirmed for 2026 — check the journal's author page.
A26: Communications & Networking | B26: IEEE Open Journal of the Communications Society | C26: OJ-COMS | D26: Open journal | E26: Fully open access | F26: =INDEX('Pricing rules'!$B$4:$B$6,MATCH(E26,'Pricing rules'!$A$4:$A$6,0)) | G26: =ROUND(F26*(1-'Pricing rules'!$B$10),0) | H26: Not available — OA only | I26: ~3.2 weeks to first decision (2021 figure) | J26: Official (IEEE notice, 2021) | K26: https://ieeexplore.ieee.org/document/9689920/ | M26: APC US$2,160 confirmed by ComSoc for 2026.
A27: Signal, Image & Speech Processing | B27: IEEE Transactions on Signal Processing | C27: TSP | D27: Transactions | E27: Hybrid | F27: =INDEX('Pricing rules'!$B$4:$B$6,MATCH(E27,'Pricing rules'!$A$4:$A$6,0)) | G27: =ROUND(F27*(1-'Pricing rules'!$B$10),0) | H27: Free (overlength page charges may apply) | I27: 3–5 months to first decision | J27: Third-party estimate | K27: https://manusights.com/blog/ieee-transactions-on-signal-processing-submission-process
A28: Signal, Image & Speech Processing | B28: IEEE Signal Processing Letters | C28: SPL | D28: Letters | E28: Hybrid | F28: =INDEX('Pricing rules'!$B$4:$B$6,MATCH(E28,'Pricing rules'!$A$4:$A$6,0)) | G28: =ROUND(F28*(1-'Pricing rules'!$B$10),0) | H28: Free (overlength page charges may apply) | I28: ~1.3 months first review round | J28: Crowd-sourced (SciRev) | K28: https://scirev.org/journal/ieee-signal-processing-letters/
A29: Signal, Image & Speech Processing | B29: IEEE Journal of Selected Topics in Signal Processing | C29: JSTSP | D29: Journal | E29: Hybrid | F29: =INDEX('Pricing rules'!$B$4:$B$6,MATCH(E29,'Pricing rules'!$A$4:$A$6,0)) | G29: =ROUND(F29*(1-'Pricing rules'!$B$10),0) | H29: Free (overlength page charges may apply) | I29: 4–8 months (varies by special issue) | J29: Third-party estimate | K29: https://manusights.com/blog/average-review-times-100-journals-2026 | M29: Special-issue driven.
A30: Signal, Image & Speech Processing | B30: IEEE Transactions on Image Processing | C30: TIP | D30: Transactions | E30: Hybrid | F30: =INDEX('Pricing rules'!$B$4:$B$6,MATCH(E30,'Pricing rules'!$A$4:$A$6,0)) | G30: =ROUND(F30*(1-'Pricing rules'!$B$10),0) | H30: Free (overlength page charges may apply) | I30: Not published
A31: Signal, Image & Speech Processing | B31: IEEE/ACM Transactions on Audio, Speech, and Language Processing | C31: TASLP | D31: Transactions | E31: Hybrid | F31: =INDEX('Pricing rules'!$B$4:$B$6,MATCH(E31,'Pricing rules'!$A$4:$A$6,0)) | G31: =ROUND(F31*(1-'Pricing rules'!$B$10),0) | H31: Free (overlength page charges may apply) | I31: Not published
A32: Signal, Image & Speech Processing | B32: IEEE Transactions on Information Forensics and Security | C32: TIFS | D32: Transactions | E32: Hybrid | F32: =INDEX('Pricing rules'!$B$4:$B$6,MATCH(E32,'Pricing rules'!$A$4:$A$6,0)) | G32: =ROUND(F32*(1-'Pricing rules'!$B$10),0) | H32: Free (overlength page charges may apply) | I32: Not published
A33: Signal, Image & Speech Processing | B33: IEEE Transactions on Multimedia | C33: TMM | D33: Transactions | E33: Hybrid | F33: =INDEX('Pricing rules'!$B$4:$B$6,MATCH(E33,'Pricing rules'!$A$4:$A$6,0)) | G33: =ROUND(F33*(1-'Pricing rules'!$B$10),0) | H33: Free (overlength page charges may apply) | I33: Not published
A34: Signal, Image & Speech Processing | B34: IEEE Transactions on Computational Imaging | C34: TCI | D34: Transactions | E34: Hybrid | F34: =INDEX('Pricing rules'!$B$4:$B$6,MATCH(E34,'Pricing rules'!$A$4:$A$6,0)) | G34: =ROUND(F34*(1-'Pricing rules'!$B$10),0) | H34: Free (overlength page charges may apply) | I34: Not published
A35: Signal, Image & Speech Processing | B35: IEEE Transactions on Signal and Information Processing over Networks | C35: TSIPN | D35: Transactions | E35: Hybrid | F35: =INDEX('Pricing rules'!$B$4:$B$6,MATCH(E35,'Pricing rules'!$A$4:$A$6,0)) | G35: =ROUND(F35*(1-'Pricing rules'!$B$10),0) | H35: Free (overlength page charges may apply) | I35: Not published
A36: Signal, Image & Speech Processing | B36: IEEE Transactions on Circuits and Systems for Video Technology | C36: TCSVT | D36: Transactions | E36: Hybrid | F36: =INDEX('Pricing rules'!$B$4:$B$6,MATCH(E36,'Pricing rules'!$A$4:$A$6,0)) | G36: =ROUND(F36*(1-'Pricing rules'!$B$10),0) | H36: Free (overlength page charges may apply) | I36: Not published
A37: Signal, Image & Speech Processing | B37: IEEE Open Journal of Signal Processing | C37: OJSP | D37: Open journal | E37: Fully open access | F37: =INDEX('Pricing rules'!$B$4:$B$6,MATCH(E37,'Pricing rules'!$A$4:$A$6,0)) | G37: =ROUND(F37*(1-'Pricing rules'!$B$10),0) | H37: Not available — OA only | I37: Target 15 weeks to accept/reject (regular papers) | J37: Official target (IEEE SPS) | K37: https://signalprocessingsociety.org/publications-resources/ieee-open-journal-signal-processing/information-authors-ojsp | M37: APC US$2,160 (2026); no overlength charges; US$1,500 for the conference section with a promo code.
A38: AI, Computing & Software | B38: IEEE Transactions on Pattern Analysis and Machine Intelligence | C38: TPAMI | D38: Transactions | E38: Hybrid | F38: =INDEX('Pricing rules'!$B$4:$B$6,MATCH(E38,'Pricing rules'!$A$4:$A$6,0)) | G38: =ROUND(F38*(1-'Pricing rules'!$B$10),0) | H38: Free (overlength page charges may apply) | I38: Not published
A39: AI, Computing & Software | B39: IEEE Transactions on Neural Networks and Learning Systems | C39: TNNLS | D39: Transactions | E39: Hybrid | F39: =INDEX('Pricing rules'!$B$4:$B$6,MATCH(E39,'Pricing rules'!$A$4:$A$6,0)) | G39: =ROUND(F39*(1-'Pricing rules'!$B$10),0) | H39: Free (overlength page charges may apply) | I39: Not published
A40: AI, Computing & Software | B40: IEEE Transactions on Artificial Intelligence | C40: TAI | D40: Transactions | E40: Hybrid | F40: =INDEX('Pricing rules'!$B$4:$B$6,MATCH(E40,'Pricing rules'!$A$4:$A$6,0)) | G40: =ROUND(F40*(1-'Pricing rules'!$B$10),0) | H40: Free (overlength page charges may apply) | I40: ~12 weeks to first decision | J40: Official (IEEE CIS) | K40: https://cis.ieee.org/publications/ieee-transactions-on-artificial-intelligence/review-process
A41: AI, Computing & Software | B41: IEEE Transactions on Cybernetics | C41: TCYB | D41: Transactions | E41: Hybrid | F41: =INDEX('Pricing rules'!$B$4:$B$6,MATCH(E41,'Pricing rules'!$A$4:$A$6,0)) | G41: =ROUND(F41*(1-'Pricing rules'!$B$10),0) | H41: Free (overlength page charges may apply) | I41: Not published
A42: AI, Computing & Software | B42: IEEE Transactions on Fuzzy Systems | C42: TFS | D42: Transactions | E42: Hybrid | F42: =INDEX('Pricing rules'!$B$4:$B$6,MATCH(E42,'Pricing rules'!$A$4:$A$6,0)) | G42: =ROUND(F42*(1-'Pricing rules'!$B$10),0) | H42: Free (overlength page charges may apply) | I42: Not published
A43: AI, Computing & Software | B43: IEEE Transactions on Evolutionary Computation | C43: TEVC | D43: Transactions | E43: Hybrid | F43: =INDEX('Pricing rules'!$B$4:$B$6,MATCH(E43,'Pricing rules'!$A$4:$A$6,0)) | G43: =ROUND(F43*(1-'Pricing rules'!$B$10),0) | H43: Free (overlength page charges may apply) | I43: Not published
A44: AI, Computing & Software | B44: IEEE Transactions on Emerging Topics in Computational Intelligence | C44: TETCI | D44: Transactions | E44: Hybrid | F44: =INDEX('Pricing rules'!$B$4:$B$6,MATCH(E44,'Pricing rules'!$A$4:$A$6,0)) | G44: =ROUND(F44*(1-'Pricing rules'!$B$10),0) | H44: Free (overlength page charges may apply) | I44: Not published
A45: AI, Computing & Software | B45: IEEE Transactions on Cognitive and Developmental Systems | C45: TCDS | D45: Transactions | E45: Hybrid | F45: =INDEX('Pricing rules'!$B$4:$B$6,MATCH(E45,'Pricing rules'!$A$4:$A$6,0)) | G45: =ROUND(F45*(1-'Pricing rules'!$B$10),0) | H45: Free (overlength page charges may apply) | I45: Not published
A46: AI, Computing & Software | B46: IEEE Transactions on Games | C46: ToG | D46: Transactions | E46: Hybrid | F46: =INDEX('Pricing rules'!$B$4:$B$6,MATCH(E46,'Pricing rules'!$A$4:$A$6,0)) | G46: =ROUND(F46*(1-'Pricing rules'!$B$10),0) | H46: Free (overlength page charges may apply) | I46: Not published
A47: AI, Computing & Software | B47: IEEE Transactions on Computers | C47: TC | D47: Transactions | E47: Hybrid | F47: =INDEX('Pricing rules'!$B$4:$B$6,MATCH(E47,'Pricing rules'!$A$4:$A$6,0)) | G47: =ROUND(F47*(1-'Pricing rules'!$B$10),0) | H47: Free (overlength page charges may apply) | I47: Not published
A48: AI, Computing & Software | B48: IEEE Transactions on Software Engineering | C48: TSE | D48: Transactions | E48: Hybrid | F48: =INDEX('Pricing rules'!$B$4:$B$6,MATCH(E48,'Pricing rules'!$A$4:$A$6,0)) | G48: =ROUND(F48*(1-'Pricing rules'!$B$10),0) | H48: Free (overlength page charges may apply) | I48: Not published
A49: AI, Computing & Software | B49: IEEE Transactions on Knowledge and Data Engineering | C49: TKDE | D49: Transactions | E49: Hybrid | F49: =INDEX('Pricing rules'!$B$4:$B$6,MATCH(E49,'Pricing rules'!$A$4:$A$6,0)) | G49: =ROUND(F49*(1-'Pricing rules'!$B$10),0) | H49: Free (overlength page charges may apply) | I49: Not published
A50: AI, Computing & Software | B50: IEEE Transactions on Parallel and Distributed Systems | C50: TPDS | D50: Transactions | E50: Hybrid | F50: =INDEX('Pricing rules'!$B$4:$B$6,MATCH(E50,'Pricing rules'!$A$4:$A$6,0)) | G50: =ROUND(F50*(1-'Pricing rules'!$B$10),0) | H50: Free (overlength page charges may apply) | I50: Not published
A51: AI, Computing & Software | B51: IEEE Transactions on Dependable and Secure Computing | C51: TDSC | D51: Transactions | E51: Hybrid | F51: =INDEX('Pricing rules'!$B$4:$B$6,MATCH(E51,'Pricing rules'!$A$4:$A$6,0)) | G51: =ROUND(F51*(1-'Pricing rules'!$B$10),0) | H51: Free (overlength page charges may apply) | I51: Not published
A52: AI, Computing & Software | B52: IEEE Transactions on Visualization and Computer Graphics | C52: TVCG | D52: Transactions | E52: Hybrid | F52: =INDEX('Pricing rules'!$B$4:$B$6,MATCH(E52,'Pricing rules'!$A$4:$A$6,0)) | G52: =ROUND(F52*(1-'Pricing rules'!$B$10),0) | H52: Free (overlength page charges may apply) | I52: Not published
... A66: AI, Computing & Software | B66: IEEE Open Journal of the Computer Society | C66: OJ-CS | D66: Open journal | E66: Fully open access | F66: =INDEX('Pricing rules'!$B$4:$B$6,MATCH(E66,'Pricing rules'!$A$4:$A$6,0)) | G66: =ROUND(F66*(1-'Pricing rules'!$B$10),0) | H66: Not available — OA only | I66: Not published
A67: AI, Computing & Software | B67: IEEE Access | C67: ACCESS | D67: Open journal | E67: Fully open access | F67: =INDEX('Pricing rules'!$B$4:$B$6,MATCH(E67,'Pricing rules'!$A$4:$A$6,0)) | G67: =ROUND(F67*(1-'Pricing rules'!$B$10),0) | H67: Not available — OA only | I67: ~4 weeks to accept/reject | J67: IEEE-stated (reported by third party) | K67: https://manusights.com/blog/ieee-access-review-time | M67: Multidisciplinary mega-journal. APC US$2,160 confirmed for 2026.
A68: Antennas, Microwaves & EM | B68: IEEE Transactions on Antennas and Propagation | C68: TAP | D68: Transactions | E68: Hybrid | F68: =INDEX('Pricing rules'!$B$4:$B$6,MATCH(E68,'Pricing rules'!$A$4:$A$6,0)) | G68: =ROUND(F68*(1-'Pricing rules'!$B$10),0) | H68: Free (overlength page charges may apply) | I68: ~12 weeks to first decision | J68: Official (IEEE APS FAQ, ~2024) | K68: https://ieeeaps.org/ieee-tap/for-authors/faqs
A69: Antennas, Microwaves & EM | B69: IEEE Antennas and Wireless Propagation Letters | C69: AWPL | D69: Letters | E69: Hybrid | F69: =INDEX('Pricing rules'!$B$4:$B$6,MATCH(E69,'Pricing rules'!$A$4:$A$6,0)) | G69: =ROUND(F69*(1-'Pricing rules'!$B$10),0) | H69: Free (overlength page charges may apply) | I69: Not published
A70: Antennas, Microwaves & EM | B70: IEEE Open Journal of Antennas and Propagation | C70: OJAP | D70: Open journal | E70: Fully open access | F70: =INDEX('Pricing rules'!$B$4:$B$6,MATCH(E70,'Pricing rules'!$A$4:$A$6,0)) | G70: =ROUND(F70*(1-'Pricing rules'!$B$10),0) | H70: Not available — OA only | I70: Not published | M70: APC US$2,160 in the 2026 CONCERT list.
A71: Antennas, Microwaves & EM | B71: IEEE Journal on Multiscale and Multiphysics Computational Techniques | C71: JMMCT | D71: Journal | E71: Hybrid | F71: =INDEX('Pricing rules'!$B$4:$B$6,MATCH(E71,'Pricing rules'!$A$4:$A$6,0)) | G71: =ROUND(F71*(1-'Pricing rules'!$B$10),0) | H71: Free (overlength page charges may apply) | I71: Not published
A72: Antennas, Microwaves & EM | B72: IEEE Transactions on Microwave Theory and Techniques | C72: TMTT | D72: Transactions | E72: Hybrid | F72: =INDEX('Pricing rules'!$B$4:$B$6,MATCH(E72,'Pricing rules'!$A$4:$A$6,0)) | G72: =ROUND(F72*(1-'Pricing rules'!$B$10),0) | H72: Free (overlength page charges may apply) | I72: Not published
A73: Antennas, Microwaves & EM | B73: IEEE Microwave and Wireless Technology Letters | C73: MWTL | D73: Letters | E73: Hybrid | F73: =INDEX('Pricing rules'!$B$4:$B$6,MATCH(E73,'Pricing rules'!$A$4:$A$6,0)) | G73: =ROUND(F73*(1-'Pricing rules'!$B$10),0) | H73: Free (overlength page charges may apply) | I73: Not published
A74: Antennas, Microwaves & EM | B74: IEEE Journal of Microwaves | C74: JMW | D74: Journal | E74: Fully open access | F74: =INDEX('Pricing rules'!$B$4:$B$6,MATCH(E74,'Pricing rules'!$A$4:$A$6,0)) | G74: =ROUND(F74*(1-'Pricing rules'!$B$10),0) | H74: Not available — OA only | I74: Not published
A75: Antennas, Microwaves & EM | B75: IEEE Transactions on Terahertz Science and Technology | C75: TTHZ | D75: Transactions | E75: Hybrid | F75: =INDEX('Pricing rules'!$B$4:$B$6,MATCH(E75,'Pricing rules'!$A$4:$A$6,0)) | G75: =ROUND(F75*(1-'Pricing rules'!$B$10),0) | H75: Free (overlength page charges may apply) | I75: Not published
A76: Antennas, Microwaves & EM | B76: IEEE Journal of Electromagnetics, RF and Microwaves in Medicine and Biology | C76: J-ERM | D76: Journal | E76: Hybrid | F76: =INDEX('Pricing rules'!$B$4:$B$6,MATCH(E76,'Pricing rules'!$A$4:$A$6,0)) | G76: =ROUND(F76*(1-'Pricing rules'!$B$10),0) | H76: Free (overlength page charges may apply) | I76: Not published
A77: Antennas, Microwaves & EM | B77: IEEE Transactions on Electromagnetic Compatibility | C77: TEMC | D77: Transactions | E77: Hybrid | F77: =INDEX('Pricing rules'!$B$4:$B$6,MATCH(E77,'Pricing rules'!$A$4:$A$6,0)) | G77: =ROUND(F77*(1-'Pricing rules'!$B$10),0) | H77: Free (overlength page charges may apply) | I77: Not published
A78: Antennas, Microwaves & EM | B78: IEEE Letters on Electromagnetic Compatibility Practice and Applications | C78: L-EMCPA | D78: Letters | E78: Hybrid | F78: =INDEX('Pricing rules'!$B$4:$B$6,MATCH(E78,'Pricing rules'!$A$4:$A$6,0)) | G78: =ROUND(F78*(1-'Pricing rules'!$B$10),0) | H78: Free (overlength page charges may apply) | I78: Not published
A79: Antennas, Microwaves & EM | B79: IEEE Transactions on Magnetics | C79: TMAG | D79: Transactions | E79: Hybrid | F79: =INDEX('Pricing rules'!$B$4:$B$6,MATCH(E79,'Pricing rules'!$A$4:$A$6,0)) | G79: =ROUND(F79*(1-'Pricing rules'!$B$10),0) | H79: Free (overlength page charges may apply) | I79: Not published
A80: Antennas, Microwaves & EM | B80: IEEE Magnetics Letters | C80: LMAG | D80: Letters | E80: Hybrid | F80: =INDEX('Pricing rules'!$B$4:$B$6,MATCH(E80,'Pricing rules'!$A$4:$A$6,0)) | G80: =ROUND(F80*(1-'Pricing rules'!$B$10),0) | H80: Free (overlength page charges may apply) | I80: Not published
A81: Photonics, Quantum & Plasma | B81: IEEE Photonics Journal | C81: PJ | D81: Journal | E81: Fully open access | F81: =INDEX('Pricing rules'!$B$4:$B$6,MATCH(E81,'Pricing rules'!$A$4:$A$6,0)) | G81: =ROUND(F81*(1-'Pricing rules'!$B$10),0) | H81: Not available — OA only | I81: Not published
A82: Photonics, Quantum & Plasma | B82: IEEE Photonics Technology Letters | C82: PTL | D82: Letters | E82: Hybrid | F82: =INDEX('Pricing rules'!$B$4:$B$6,MATCH(E82,'Pricing rules'!$A$4:$A$6,0)) | G82: =ROUND(F82*(1-'Pricing rules'!$B$10),0) | H82: Free (overlength page charges may apply) | I82: Not published
... A89: Photonics, Quantum & Plasma | B89: IEEE Transactions on Nuclear Science | C89: TNS | D89: Transactions | E89: Hybrid | F89: =INDEX('Pricing rules'!$B$4:$B$6,MATCH(E89,'Pricing rules'!$A$4:$A$6,0)) | G89: =ROUND(F89*(1-'Pricing rules'!$B$10),0) | H89: Free (overlength page charges may apply) | I89: Not published
A90: Geoscience, Remote Sensing & Ocean | B90: IEEE Transactions on Geoscience and Remote Sensing | C90: TGRS | D90: Transactions | E90: Hybrid | F90: =INDEX('Pricing rules'!$B$4:$B$6,MATCH(E90,'Pricing rules'!$A$4:$A$6,0)) | G90: =ROUND(F90*(1-'Pricing rules'!$B$10),0) | H90: Free (overlength page charges may apply) | I90: Not published | M90: Overlength charge US$230/page beyond 10 pages (2026).
A91: Geoscience, Remote Sensing & Ocean | B91: IEEE Geoscience and Remote Sensing Letters | C91: GRSL | D91: Letters | E91: Hybrid | F91: =INDEX('Pricing rules'!$B$4:$B$6,MATCH(E91,'Pricing rules'!$A$4:$A$6,0)) | G91: =ROUND(F91*(1-'Pricing rules'!$B$10),0) | H91: Free (overlength page charges may apply) | I91: Not published
A92: Geoscience, Remote Sensing & Ocean | B92: IEEE Journal of Selected Topics in Applied Earth Observations and Remote Sensing | C92: JSTARS | D92: Journal | E92: Fully open access | F92: =INDEX('Pricing rules'!$B$4:$B$6,MATCH(E92,'Pricing rules'!$A$4:$A$6,0)) | G92: =ROUND(F92*(1-'Pricing rules'!$B$10),0) | H92: Not available — OA only | I92: Not published
A93: Geoscience, Remote Sensing & Ocean | B93: IEEE Journal of Oceanic Engineering | C93: JOE | D93: Journal | E93: Hybrid | F93: =INDEX('Pricing rules'!$B$4:$B$6,MATCH(E93,'Pricing rules'!$A$4:$A$6,0)) | G93: =ROUND(F93*(1-'Pricing rules'!$B$10),0) | H93: Free (overlength page charges may apply) | I93: Not published
A94: Circuits, Devices & Semiconductors | B94: IEEE Transactions on Circuits and Systems I: Regular Papers | C94: TCAS-I | D94: Transactions | E94: Hybrid | F94: =INDEX('Pricing rules'!$B$4:$B$6,MATCH(E94,'Pricing rules'!$A$4:$A$6,0)) | G94: =ROUND(F94*(1-'Pricing rules'!$B$10),0) | H94: Free (overlength page charges may apply) | I94: Not published
A95: Circuits, Devices & Semiconductors | B95: IEEE Transactions on Circuits and Systems II: Express Briefs | C95: TCAS-II | D95: Transactions | E95: Hybrid | F95: =INDEX('Pricing rules'!$B$4:$B$6,MATCH(E95,'Pricing rules'!$A$4:$A$6,0)) | G95: =ROUND(F95*(1-'Pricing rules'!$B$10),0) | H95: Free (overlength page charges may apply) | I95: Not published
A96: Circuits, Devices & Semiconductors | B96: IEEE Journal on Emerging and Selected Topics in Circuits and Systems | C96: JETCAS | D96: Journal | E96: Hybrid | F96: =INDEX('Pricing rules'!$B$4:$B$6,MATCH(E96,'Pricing rules'!$A$4:$A$6,0)) | G96: =ROUND(F96*(1-'Pricing rules'!$B$10),0) | H96: Free (overlength page charges may apply) | I96: Not published
A97: Circuits, Devices & Semiconductors | B97: IEEE Transactions on Biomedical Circuits and Systems | C97: TBioCAS | D97: Transactions | E97: Hybrid | F97: =INDEX('Pricing rules'!$B$4:$B$6,MATCH(E97,'Pricing rules'!$A$4:$A$6,0)) | G97: =ROUND(F97*(1-'Pricing rules'!$B$10),0) | H97: Free (overlength page charges may apply) | I97: Not published
A98: Circuits, Devices & Semiconductors | B98: IEEE Transactions on Very Large Scale Integration (VLSI) Systems | C98: TVLSI | D98: Transactions | E98: Hybrid | F98: =INDEX('Pricing rules'!$B$4:$B$6,MATCH(E98,'Pricing rules'!$A$4:$A$6,0)) | G98: =ROUND(F98*(1-'Pricing rules'!$B$10),0) | H98: Free (overlength page charges may apply) | I98: Not published
A99: Circuits, Devices & Semiconductors | B99: IEEE Transactions on Computer-Aided Design of Integrated Circuits and Systems | C99: TCAD | D99: Transactions | E99: Hybrid | F99: =INDEX('Pricing rules'!$B$4:$B$6,MATCH(E99,'Pricing rules'!$A$4:$A$6,0)) | G99: =ROUND(F99*(1-'Pricing rules'!$B$10),0) | H99: Free (overlength page charges may apply) | I99: Not published
A100: Circuits, Devices & Semiconductors | B100: IEEE Open Journal of Circuits and Systems | C100: OJCAS | D100: Open journal | E100: Fully open access | F100: =INDEX('Pricing rules'!$B$4:$B$6,MATCH(E100,'Pricing rules'!$A$4:$A$6,0)) | G100: =ROUND(F100*(1-'Pricing rules'!$B$10),0) | H100: Not available — OA only | I100: Not published | M100: APC US$2,160 in the 2026 CONCERT list.
A101: Circuits, Devices & Semiconductors | B101: IEEE Journal of Solid-State Circuits | C101: JSSC | D101: Journal | E101: Hybrid | F101: =INDEX('Pricing rules'!$B$4:$B$6,MATCH(E101,'Pricing rules'!$A$4:$A$6,0)) | G101: =ROUND(F101*(1-'Pricing rules'!$B$10),0) | H101: Free (overlength page charges may apply) | I101: Not published
A102: Circuits, Devices & Semiconductors | B102: IEEE Solid-State Circuits Letters | C102: SSC-L | D102: Letters | E102: Hybrid | F102: =INDEX('Pricing rules'!$B$4:$B$6,MATCH(E102,'Pricing rules'!$A$4:$A$6,0)) | G102: =ROUND(F102*(1-'Pricing rules'!$B$10),0) | H102: Free (overlength page charges may apply) | I102: Not published
A103: Circuits, Devices & Semiconductors | B103: IEEE Open Journal of the Solid-State Circuits Society | C103: OJSSCS | D103: Open journal | E103: Fully open access | F103: =INDEX('Pricing rules'!$B$4:$B$6,MATCH(E103,'Pricing rules'!$A$4:$A$6,0)) | G103: =ROUND(F103*(1-'Pricing rules'!$B$10),0) | H103: Not available — OA only | I103: Not published
A104: Circuits, Devices & Semiconductors | B104: IEEE Transactions on Electron Devices | C104: TED | D104: Transactions | E104: Hybrid | F104: =INDEX('Pricing rules'!$B$4:$B$6,MATCH(E104,'Pricing rules'!$A$4:$A$6,0)) | G104: =ROUND(F104*(1-'Pricing rules'!$B$10),0) | H104: Free (overlength page charges may apply) | I104: Not published
A105: Circuits, Devices & Semiconductors | B105: IEEE Electron Device Letters | C105: EDL | D105: Letters | E105: Hybrid | F105: =INDEX('Pricing rules'!$B$4:$B$6,MATCH(E105,'Pricing rules'!$A$4:$A$6,0)) | G105: =ROUND(F105*(1-'Pricing rules'!$B$10),0) | H105: Free (overlength page charges may apply) | I105: Not published
A106: Circuits, Devices & Semiconductors | B106: IEEE Journal of the Electron Devices Society | C106: J-EDS | D106: Journal | E106: Fully open access | F106: =INDEX('Pricing rules'!$B$4:$B$6,MATCH(E106,'Pricing rules'!$A$4:$A$6,0)) | G106: =ROUND(F106*(1-'Pricing rules'!$B$10),0) | H106: Not available — OA only | I106: Not published
A107: Circuits, Devices & Semiconductors | B107: IEEE Journal on Exploratory Solid-State Computational Devices and Circuits | C107: JXCDC | D107: Journal | E107: Fully open access | F107: =INDEX('Pricing rules'!$B$4:$B$6,MATCH(E107,'Pricing rules'!$A$4:$A$6,0)) | G107: =ROUND(F107*(1-'Pricing rules'!$B$10),0) | H107: Not available — OA only | I107: Not published
A108: Circuits, Devices & Semiconductors | B108: IEEE Transactions on Semiconductor Manufacturing | C108: TSM | D108: Transactions | E108: Hybrid | F108: =INDEX('Pricing rules'!$B$4:$B$6,MATCH(E108,'Pricing rules'!$A$4:$A$6,0)) | G108: =ROUND(F108*(1-'Pricing rules'!$B$10),0) | H108: Free (overlength page charges may apply) | I108: Not published
A109: Circuits, Devices & Semiconductors | B109: IEEE Transactions on Device and Materials Reliability | C109: TDMR | D109: Transactions | E109: Hybrid | F109: =INDEX('Pricing rules'!$B$4:$B$6,MATCH(E109,'Pricing rules'!$A$4:$A$6,0)) | G109: =ROUND(F109*(1-'Pricing rules'!$B$10),0) | H109: Free (overlength page charges may apply) | I109: Not published
A110: Circuits, Devices & Semiconductors | B110: IEEE Transactions on Components, Packaging and Manufacturing Technology | C110: TCPMT | D110: Transactions | E110: Hybrid | F110: =INDEX('Pricing rules'!$B$4:$B$6,MATCH(E110,'Pricing rules'!$A$4:$A$6,0)) | G110: =ROUND(F110*(1-'Pricing rules'!$B$10),0) | H110: Free (overlength page charges may apply) | I110: Not published
A111: Circuits, Devices & Semiconductors | B111: IEEE Transactions on Nanotechnology | C111: TNANO | D111: Transactions | E111: Hybrid | F111: =INDEX('Pricing rules'!$B$4:$B$6,MATCH(E111,'Pricing rules'!$A$4:$A$6,0)) | G111: =ROUND(F111*(1-'Pricing rules'!$B$10),0) | H111: Free (overlength page charges may apply) | I111: Not published
A112: Circuits, Devices & Semiconductors | B112: IEEE Open Journal of Nanotechnology | C112: OJNANO | D112: Open journal | E112: Fully open access | F112: =INDEX('Pricing rules'!$B$4:$B$6,MATCH(E112,'Pricing rules'!$A$4:$A$6,0)) | G112: =ROUND(F112*(1-'Pricing rules'!$B$10),0) | H112: Not available — OA only | I112: Not published
... A120: Power, Energy & Industrial Electronics | B120: IEEE Transactions on Power Delivery | C120: TPWRD | D120: Transactions | E120: Hybrid | F120: =INDEX('Pricing rules'!$B$4:$B$6,MATCH(E120,'Pricing rules'!$A$4:$A$6,0)) | G120: =ROUND(F120*(1-'Pricing rules'!$B$10),0) | H120: Free (overlength page charges may apply) | I120: Not published
A121: Power, Energy & Industrial Electronics | B121: IEEE Transactions on Energy Markets, Policy and Regulation | C121: TEMPR | D121: Transactions | E121: Hybrid | F121: =INDEX('Pricing rules'!$B$4:$B$6,MATCH(E121,'Pricing rules'!$A$4:$A$6,0)) | G121: =ROUND(F121*(1-'Pricing rules'!$B$10),0) | H121: Free (overlength page charges may apply) | I121: Not published | M121: Open-access model not confirmed for 2026 — check the journal's author page.
A122: Power, Energy & Industrial Electronics | B122: IEEE Open Access Journal of Power and Energy | C122: OAJPE | D122: Open journal | E122: Fully open access | F122: =INDEX('Pricing rules'!$B$4:$B$6,MATCH(E122,'Pricing rules'!$A$4:$A$6,0)) | G122: =ROUND(F122*(1-'Pricing rules'!$B$10),0) | H122: Not available — OA only | I122: Not published | M122: APC US$2,160 confirmed by IEEE PES for 2026.
A123: Power, Energy & Industrial Electronics | B123: IEEE Transactions on Power Electronics | C123: TPEL | D123: Transactions | E123: Hybrid | F123: =INDEX('Pricing rules'!$B$4:$B$6,MATCH(E123,'Pricing rules'!$A$4:$A$6,0)) | G123: =ROUND(F123*(1-'Pricing rules'!$B$10),0) | H123: Free (overlength page charges may apply) | I123: Not published
A124: Power, Energy & Industrial Electronics | B124: IEEE Journal of Emerging and Selected Topics in Power Electronics | C124: JESTPE | D124: Journal | E124: Hybrid | F124: =INDEX('Pricing rules'!$B$4:$B$6,MATCH(E124,'Pricing rules'!$A$4:$A$6,0)) | G124: =ROUND(F124*(1-'Pricing rules'!$B$10),0) | H124: Free (overlength page charges may apply) | I124: Not published
A125: Power, Energy & Industrial Electronics | B125: IEEE Open Journal of Power Electronics | C125: OJPEL | D125: Open journal | E125: Fully open access | F125: =INDEX('Pricing rules'!$B$4:$B$6,MATCH(E125,'Pricing rules'!$A$4:$A$6,0)) | G125: =ROUND(F125*(1-'Pricing rules'!$B$10),0) | H125: Not available — OA only | I125: Not published
A126: Power, Energy & Industrial Electronics | B126: IEEE Transactions on Industrial Electronics | C126: TIE | D126: Transactions | E126: Hybrid | F126: =INDEX('Pricing rules'!$B$4:$B$6,MATCH(E126,'Pricing rules'!$A$4:$A$6,0)) | G126: =ROUND(F126*(1-'Pricing rules'!$B$10),0) | H126: Free (overlength page charges may apply) | I126: Not published
...

Sheet Magazines
A1: Track | B1: Journal | C1: Acronym | D1: Type | E1: OA model | F1: APC 2026 (US$) | G1: APC for society member (US$) | H1: Cost without OA | I1: Avg. time to first decision | J1: Decision-time source | K1: Source link | L1: Society | M1: Notes
A2: Aerospace, Radar & Navigation | B2: IEEE Aerospace and Electronic Systems Magazine | C2: AESM | D2: Magazine | E2: Hybrid magazine | F2: =INDEX('Pricing rules'!$B$4:$B$6,MATCH(E2,'Pricing rules'!$A$4:$A$6,0)) | G2: =ROUND(F2*(1-'Pricing rules'!$B$10),0) | H2: Free (most articles are invited) | I2: Not published | L2: AESS
A3: Communications & Networking | B3: IEEE Communications Magazine | C3: COMMAG | D3: Magazine | E3: Hybrid magazine | F3: =INDEX('Pricing rules'!$B$4:$B$6,MATCH(E3,'Pricing rules'!$A$4:$A$6,0)) | G3: =ROUND(F3*(1-'Pricing rules'!$B$10),0) | H3: Free (most articles are invited) | I3: Not published
A4: Communications & Networking | B4: IEEE Network | C4: NET | D4: Magazine | E4: Hybrid magazine | F4: =INDEX('Pricing rules'!$B$4:$B$6,MATCH(E4,'Pricing rules'!$A$4:$A$6,0)) | G4: =ROUND(F4*(1-'Pricing rules'!$B$10),0) | H4: Free (most articles are invited) | I4: Not published
A5: Communications & Networking | B5: IEEE Wireless Communications | C5: WC | D5: Magazine | E5: Hybrid magazine | F5: =INDEX('Pricing rules'!$B$4:$B$6,MATCH(E5,'Pricing rules'!$A$4:$A$6,0)) | G5: =ROUND(F5*(1-'Pricing rules'!$B$10),0) | H5: Free (most articles are invited) | I5: Not published
A6: Communications & Networking | B6: IEEE Internet of Things Magazine | C6: IoTM | D6: Magazine | E6: Hybrid magazine | F6: =INDEX('Pricing rules'!$B$4:$B$6,MATCH(E6,'Pricing rules'!$A$4:$A$6,0)) | G6: =ROUND(F6*(1-'Pricing rules'!$B$10),0) | H6: Free (most articles are invited) | I6: Not published
A7: Communications & Networking | B7: IEEE Communications Standards Magazine | C7: COMSTD | D7: Magazine | E7: Hybrid magazine | F7: =INDEX('Pricing rules'!$B$4:$B$6,MATCH(E7,'Pricing rules'!$A$4:$A$6,0)) | G7: =ROUND(F7*(1-'Pricing rules'!$B$10),0) | H7: Free (most articles are invited) | I7: Not published
A8: Communications & Networking | B8: IEEE BITS the Information Theory Magazine | C8: BITS | D8: Magazine | E8: Hybrid magazine | F8: =INDEX('Pricing rules'!$B$4:$B$6,MATCH(E8,'Pricing rules'!$A$4:$A$6,0)) | G8: =ROUND(F8*(1-'Pricing rules'!$B$10),0) | H8: Free (most articles are invited) | I8: Not published
A9: Vehicles & Transportation | B9: IEEE Vehicular Technology Magazine | C9: VTM | D9: Magazine | E9: Hybrid magazine | F9: =INDEX('Pricing rules'!$B$4:$B$6,MATCH(E9,'Pricing rules'!$A$4:$A$6,0)) | G9: =ROUND(F9*(1-'Pricing rules'!$B$10),0) | H9: Free (most articles are invited) | I9: Not published
A10: Vehicles & Transportation | B10: IEEE Intelligent Transportation Systems Magazine | C10: ITSM | D10: Magazine | E10: Hybrid magazine | F10: =INDEX('Pricing rules'!$B$4:$B$6,MATCH(E10,'Pricing rules'!$A$4:$A$6,0)) | G10: =ROUND(F10*(1-'Pricing rules'!$B$10),0) | H10: Free (most articles are invited) | I10: Not published
A11: Signal, Image & Speech Processing | B11: IEEE Signal Processing Magazine | C11: SPM | D11: Magazine | E11: Hybrid magazine | F11: =INDEX('Pricing rules'!$B$4:$B$6,MATCH(E11,'Pricing rules'!$A$4:$A$6,0)) | G11: =ROUND(F11*(1-'Pricing rules'!$B$10),0) | H11: Free (most articles are invited) | I11: Not published
A12: AI, Computing & Software | B12: IEEE Computational Intelligence Magazine | C12: CIM | D12: Magazine | E12: Hybrid magazine | F12: =INDEX('Pricing rules'!$B$4:$B$6,MATCH(E12,'Pricing rules'!$A$4:$A$6,0)) | G12: =ROUND(F12*(1-'Pricing rules'!$B$10),0) | H12: Free (most articles are invited) | I12: Not published
A13: AI, Computing & Software | B13: Computer | C13: COMPUTER | D13: Magazine | E13: Hybrid magazine | F13: =INDEX('Pricing rules'!$B$4:$B$6,MATCH(E13,'Pricing rules'!$A$4:$A$6,0)) | G13: =ROUND(F13*(1-'Pricing rules'!$B$10),0) | H13: Free (most articles are invited) | I13: Not published
A14: AI, Computing & Software | B14: IEEE Software | C14: SOFTWARE | D14: Magazine | E14: Hybrid magazine | F14: =INDEX('Pricing rules'!$B$4:$B$6,MATCH(E14,'Pricing rules'!$A$4:$A$6,0)) | G14: =ROUND(F14*(1-'Pricing rules'!$B$10),0) | H14: Free (most articles are invited) | I14: Not published
... A44: Multidisciplinary, Education & Society | B44: IEEE Engineering Management Review | C44: EMR | D44: Magazine | E44: Hybrid magazine | F44: =INDEX('Pricing rules'!$B$4:$B$6,MATCH(E44,'Pricing rules'!$A$4:$A$6,0)) | G44: =ROUND(F44*(1-'Pricing rules'!$B$10),0) | H44: Free (most articles are invited) | I44: Not published
